[
  {
    "id": "acae67e7-4452-41de-b6c1-ded6107424be",
    "data": [
      {
        "text": "video player",
        "meta": "@device",
        "alias": "device",
        "userDefined": false
      },
      {
        "text": " ",
        "userDefined": false
      },
      {
        "text": "in",
        "meta": "@sys.ignore",
        "userDefined": false
      },
      {
        "text": " ",
        "userDefined": false
      },
      {
        "text": "bedroom",
        "meta": "@room",
        "alias": "room",
        "userDefined": false
      },
      {
        "text": " too please",
        "userDefined": false
      }
    ],
    "isTemplate": false,
    "count": 0,
    "lang": "en",
    "updated": 0
  },
  {
    "id": "42f4425f-b24d-4cf5-a7f5-b34893e2a89e",
    "data": [
      {
        "text": "kitchen",
        "meta": "@room",
        "alias": "room",
        "userDefined": false
      },
      {
        "text": " ",
        "userDefined": false
      },
      {
        "text": "lights",
        "meta": "@device",
        "alias": "device",
        "userDefined": false
      },
      {
        "text": " as ",
        "userDefined": false
      },
      {
        "text": "well",
        "meta": "@sys.ignore",
        "userDefined": false
      }
    ],
    "isTemplate": false,
    "count": 0,
    "lang": "en",
    "updated": 0
  },
  {
    "id": "55cd46e2-a7ac-4749-adfe-a128d90588d6",
    "data": [
      {
        "text": "also ",
        "userDefined": false
      },
      {
        "text": "video player",
        "meta": "@device",
        "alias": "device",
        "userDefined": false
      },
      {
        "text": " ",
        "userDefined": false
      },
      {
        "text": "in",
        "meta": "@sys.ignore",
        "userDefined": false
      },
      {
        "text": " my ",
        "userDefined": false
      },
      {
        "text": "kitchen",
        "meta": "@room",
        "alias": "room",
        "userDefined": false
      }
    ],
    "isTemplate": false,
    "count": 0,
    "lang": "en",
    "updated": 0
  },
  {
    "id": "c2c50cb6-55e8-4a7d-ab84-e253aaffbb72",
    "data": [
      {
        "text": "what about ",
        "userDefined": false
      },
      {
        "text": "thermostat",
        "meta": "@device",
        "alias": "device",
        "userDefined": false
      },
      {
        "text": " in the ",
        "userDefined": false
      },
      {
        "text": "kitchen",
        "meta": "@room",
        "alias": "room",
        "userDefined": false
      }
    ],
    "isTemplate": false,
    "count": 0,
    "lang": "en",
    "updated": 0
  },
  {
    "id": "64d7e2cd-6623-4d48-a8ee-04c82f8f383e",
    "data": [
      {
        "text": "and ",
        "userDefined": false
      },
      {
        "text": "TV",
        "meta": "@device",
        "alias": "device",
        "userDefined": false
      },
      {
        "text": " ",
        "userDefined": false
      },
      {
        "text": "in",
        "meta": "@sys.ignore",
        "userDefined": false
      },
      {
        "text": " ",
        "userDefined": false
      },
      {
        "text": "kitchen",
        "meta": "@room",
        "alias": "room",
        "userDefined": false
      },
      {
        "text": " too",
        "userDefined": false
      }
    ],
    "isTemplate": false,
    "count": 0,
    "lang": "en",
    "updated": 0
  },
  {
    "id": "b482bb5a-5905-4cbc-9434-c90c7ea5e17c",
    "data": [
      {
        "text": "what about ",
        "userDefined": false
      },
      {
        "text": "bedroom",
        "meta": "@room",
        "alias": "room",
        "userDefined": false
      },
      {
        "text": " ",
        "userDefined": false
      },
      {
        "text": "TV",
        "meta": "@device",
        "alias": "device",
        "userDefined": false
      }
    ],
    "isTemplate": false,
    "count": 0,
    "lang": "en",
    "updated": 0
  },
  {
    "id": "81ae3c65-70fa-4f59-8901-68826579f5fa",
    "data": [
      {
        "text": "and ",
        "userDefined": false
      },
      {
        "text": "TV",
        "meta": "@device",
        "alias": "device",
        "userDefined": false
      },
      {
        "text": " ",
        "userDefined": false
      },
      {
        "text": "in",
        "meta": "@sys.ignore",
        "userDefined": false
      },
      {
        "text": " ",
        "userDefined": false
      },
      {
        "text": "kitchen",
        "meta": "@room",
        "alias": "room",
        "userDefined": false
      },
      {
        "text": " as ",
        "userDefined": false
      },
      {
        "text": "well",
        "meta": "@sys.ignore",
        "userDefined": false
      }
    ],
    "isTemplate": false,
    "count": 0,
    "lang": "en",
    "updated": 0
  }
]